{
  "songs": [
    {
      "title": "蜘蛛の糸",
      "constant": 13.8,
      "difficulty": "Master"
    },
    {
      "title": "チューリングの跡",
      "constant": 13.9,
      "difficulty": "Master"
    },
    {
      "title": "雪男",
      "constant": 13.7,
      "difficulty": "Master"
    },
    {
      "title": "MarbleBlue.",
      "constant": 13.6,
      "difficulty": "Master"
    },
    {
      "title": "YURUSHITE",
      "constant": 13.8,
      "difficulty": "Master"
    },
    {
      "title": "Odin",
      "constant": 13.8,
      "difficulty": "Master"
    },
    {
      "title": "Ultimate Force",
      "constant": 13.5,
      "difficulty": "Master"
    },
    {
      "title": "黎命に殉ず",
      "constant": 13.8,
      "difficulty": "Master"
    },
    {
      "title": "A Man In The Mirror",
      "constant": 13.8,
      "difficulty": "Master"
    },
    {
      "title": "Re：End of a Dream",
      "constant": 13.8,
      "difficulty": "Master"
    },
    {
      "title": "神威",
      "constant": 13.7,
      "difficulty": "Master"
    },
    {
      "title": "ERIS -Legend of Gaidelia-",
      "constant": 15.0,
      "difficulty": "Ultima"
    },
    {
      "title": "Singularity",
      "constant": 13.7,
      "difficulty": "Master"
    },
    {
      "title": "Opfer",
      "constant": 13.8,
      "difficulty": "Master"
    },
    {
      "title": "Elemental Creation",
      "constant": 15.0,
      "difficulty": "Ultima"
    },
    {
      "title": "《創造》 ～ Cries, beyond The End",
      "constant": 13.7,
      "difficulty": "Master"
    },
    {
      "title": "Rrhar'il",
      "constant": 13.7,
      "difficulty": "Master"
    },
    {
      "title": "Disruptor Array",
      "constant": 13.6,
      "difficulty": "Master"
    },
    {
      "title": "Viyella's Tears",
      "constant": 13.7,
      "difficulty": "Master"
    },
    {
      "title": "Latent Kingdom",
      "constant": 13.7,
      "difficulty": "Master"
    },
    {
      "title": "ホーリーサンバランド",
      "constant": 13.8,
      "difficulty": "Master"
    },
    {
      "title": "SINister Evolution",
      "constant": 13.8,
      "difficulty": "Master"
    },
    {
      "title": "GIGA BLAST",
      "constant": 13.6,
      "difficulty": "Master"
    },
    {
      "title": "AstrøNotes.",
      "constant": 13.7,
      "difficulty": "Master"
    },
    {
      "title": "Titania",
      "constant": 13.7,
      "difficulty": "Master"
    },
    {
      "title": "To：Be Continued",
      "constant": 13.5,
      "difficulty": "Master"
    },
    {
      "title": "LAMIA",
      "constant": 13.6,
      "difficulty": "Master"
    },
    {
      "title": "Blackmagik Blazing",
      "constant": 13.7,
      "difficulty": "Master"
    },
    {
      "title": "FREEDOM DiVE",
      "constant": 13.7,
      "difficulty": "Master"
    },
    {
      "title": "Ascension to Heaven",
      "constant": 13.7,
      "difficulty": "Master"
    },
    {
      "title": "Crush the Dystopia",
      "constant": 13.6,
      "difficulty": "Master"
    },
    {
      "title": "Tempestissimo",
      "constant": 13.7,
      "difficulty": "Master"
    },
    {
      "title": "Synthesis.",
      "constant": 13.6,
      "difficulty": "Master"
    },
    {
      "title": "Chronomia",
      "constant": 13.7,
      "difficulty": "Master"
    },
    {
      "title": "Oracle",
      "constant": 13.6,
      "difficulty": "Master"
    },
    {
      "title": "キミとボクへの葬送歌",
      "constant": 13.3,
      "difficulty": "Master"
    },
    {
      "title": "淵底のグレイ・ユークロニア",
      "constant": 13.5,
      "difficulty": "Master"
    },
    {
      "title": "Ai C",
      "constant": 13.6,
      "difficulty": "Master"
    },
    {
      "title": "オーバーライド",
      "constant": 15.0,
      "difficulty": "Ultima"
    },
    {
      "title": "Aether Crest: Celestial",
      "constant": 13.5,
      "difficulty": "Master"
    },
    {
      "title": "The Devil Incarnate",
      "constant": 13.4,
      "difficulty": "Master"
    },
    {
      "title": "Theatore Creatore",
      "constant": 13.7,
      "difficulty": "Master"
    },
    {
      "title": "HeinousЯeaper",
      "constant": 13.4,
      "difficulty": "Master"
    },
    {
      "title": "Igallta",
      "constant": 13.5,
      "difficulty": "Master"
    },
    {
      "title": "〚献身〛 ～Paradox of Choice",
      "constant": 13.4,
      "difficulty": "Master"
    },
    {
      "title": "〚盲従〛 ～Fantasia Sonata Flower",
      "constant": 13.5,
      "difficulty": "Master"
    },
    {
      "title": "メズマライザー",
      "constant": 15.0,
      "difficulty": "Ultima"
    },
    {
      "title": "房総★ミラクル☆てんたくる!?",
      "constant": 13.6,
      "difficulty": "Master"
    },
    {
      "title": "ノンブレス・オブリージュ",
      "constant": 13.7,
      "difficulty": "Master"
    }
  ]
}

